neuro_logging/__init__.py
neuro_logging/config.py
neuro_logging/py.typed
neuro_logging/testing_utils.py
neuro_logging/trace.py
neuro_logging-25.10.0.dist-info/licenses/LICENSE
neuro_logging-25.10.0.dist-info/METADATA
neuro_logging-25.10.0.dist-info/WHEEL
neuro_logging-25.10.0.dist-info/top_level.txt
neuro_logging-25.10.0.dist-info/RECORD
