Metadata-Version: 2.4
Name: neuro-logging
Version: 25.10.0
Summary: Logging client for Neu.ro platform services
Home-page: https://github.com/neuro-inc/neuro-logging
License: Apache 2
Classifier: License :: OSI Approved :: Apache Software License
Classifier: Programming Language :: Python :: 3
Requires-Python: >=3.9
License-File: LICENSE
Requires-Dist: aiohttp<4.0,>=3.8
Requires-Dist: orjson>=3.10.12
Requires-Dist: python-json-logger>=3.2.1
Requires-Dist: sentry-sdk<2.40,>=2.19.2
Dynamic: license-file
